<?xml version="1.0" encoding="utf-8" ?>
<data>
  <!-- Changing sprite width/height is untested and will likely lead to graphical bugs -->
  <Sprite Key="RequestBoard.CompleteMark" Sheet="menuwindows" Sprite="560,600 16,16" />
  <Sprite Key="BountyBoard.CompleteMark" Sheet="menuwindows" Sprite="560,600 16,16" />
  <Sprite Key="SubChip.FullScreen" Sheet="menuwindows" Sprite="240,464 240,160" />
  <Sprite Key="SubChip.UsedChipFirewall" Sheet="menuwindows" Sprite="264,520 64,16" />
  <Sprite Key="SubChip.UsedChipOpenPort" Sheet="menuwindows" Sprite="264,536 64,16" />
  <Sprite Key="SubChip.UsedChipAnti-Vrs" Sheet="menuwindows" Sprite="264,552 64,16" />
  <Sprite Key="SubChip.UsedChipVirusScn" Sheet="menuwindows" Sprite="264,568 64,16" />
  <Sprite Key="Shop.BugFragCounter" Sheet="menuwindows" Sprite="720,712 80,40" />
  <Sprite Key="Shop.FrzFragCounter" Sheet="menuwindows" Sprite="720,752 80,40" />
  <Sprite Key="Shop.ErrFragCounter" Sheet="menuwindows" Sprite="720,792 80,40" />
  <Sprite Key="SceneTitle.LogoBorder" Sheet="title2" Sprite="240,0 240,160" />
  <Sprite Key="SceneTitle.LogoText" Sheet="title2" Sprite="0,160 240,160" />
  <Sprite Key="SceneTitle.LogoCutout" Sheet="title2" Sprite="480,160 240,160" />
  <Sprite Key="SceneTitle.NewGame" Sheet="title" Sprite="240,160 48,16" />
  <Sprite Key="SceneTitle.Continue" Sheet="title" Sprite="240,176 48,16" />
  <Sprite Key="Result.RewardNormal" Sheet="battleobjects" Sprite="240,184 192,139" />
  <Sprite Key="Result.RewardNoise" Sheet="battleobjects" Sprite="0,504 192,139" />
  <Sprite Key="Result.FragLabel" Sheet="battleobjects" Sprite="432,16 24,16" />
  <Sprite Key="FirstTitle.ScrollingTitle" Sheet="title2" Sprite="240,320 512,160" />
  <Sprite Key="FirstTitle.SpinningTitle" Sheet="title2" Sprite="0,160 240,160" />
  <Sprite Key="Custom.ProgramAdvance" Sheet="battleobjects" Sprite="464,80 88,16" />
  <Sprite Key="Custom.NoChipInfo" Sheet="battleobjects" Sprite="208,120 56,64" />
  <Sprite Key="Custom.SendChipInfo" Sheet="battleobjects" Sprite="264,120 56,64" />
  <Sprite Key="Custom.AddChipInfo1" Sheet="battleobjects" Sprite="376,120 56,64" />
  <Sprite Key="Custom.AddChipInfo2" Sheet="battleobjects" Sprite="320,120 56,64" />
  <Sprite Key="Custom.StyleNormUnselected" Sheet="battleobjects" Sprite="240,328 64,16" />
  <Sprite Key="Custom.StyleFghtUnselected" Sheet="battleobjects" Sprite="240,344 64,16" />
  <Sprite Key="Custom.StyleNinjUnselected" Sheet="battleobjects" Sprite="240,360 64,16" />
  <Sprite Key="Custom.StyleDocUnselected" Sheet="battleobjects" Sprite="240,376 64,16" />
  <Sprite Key="Custom.StyleGaiaUnselected" Sheet="battleobjects" Sprite="240,392 64,16" />
  <Sprite Key="Custom.StyleWingUnselected" Sheet="battleobjects" Sprite="240,408 64,16" />
  <Sprite Key="Custom.StyleWtchUnselected" Sheet="battleobjects" Sprite="240,424 64,16" />
  <Sprite Key="Custom.StyleNormHovered" Sheet="battleobjects" Sprite="304,328 64,16" />
  <Sprite Key="Custom.StyleFghtHovered" Sheet="battleobjects" Sprite="304,344 64,16" />
  <Sprite Key="Custom.StyleNinjHovered" Sheet="battleobjects" Sprite="304,360 64,16" />
  <Sprite Key="Custom.StyleDocHovered" Sheet="battleobjects" Sprite="304,376 64,16" />
  <Sprite Key="Custom.StyleGaiaHovered" Sheet="battleobjects" Sprite="304,392 64,16" />
  <Sprite Key="Custom.StyleWingHovered" Sheet="battleobjects" Sprite="304,408 64,16" />
  <Sprite Key="Custom.StyleWtchHovered" Sheet="battleobjects" Sprite="304,424 64,16" />
  <Sprite Key="Custom.StyleNormDisabled" Sheet="battleobjects" Sprite="368,328 64,16" />
  <Sprite Key="Custom.StyleFghtDisabled" Sheet="battleobjects" Sprite="368,344 64,16" />
  <Sprite Key="Custom.StyleNinjDisabled" Sheet="battleobjects" Sprite="368,360 64,16" />
  <Sprite Key="Custom.StyleDocDisabled" Sheet="battleobjects" Sprite="368,376 64,16" />
  <Sprite Key="Custom.StyleGaiaDisabled" Sheet="battleobjects" Sprite="368,392 64,16" />
  <Sprite Key="Custom.StyleWingDisabled" Sheet="battleobjects" Sprite="368,408 64,16" />
  <Sprite Key="Custom.StyleWtchDisabled" Sheet="battleobjects" Sprite="368,424 64,16" />
  <Sprite Key="Custom.StyleNormSelected" Sheet="battleobjects" Sprite="432,328 64,16" />
  <Sprite Key="Custom.StyleFghtSelected" Sheet="battleobjects" Sprite="432,344 64,16" />
  <Sprite Key="Custom.StyleNinjSelected" Sheet="battleobjects" Sprite="432,360 64,16" />
  <Sprite Key="Custom.StyleDocSelected" Sheet="battleobjects" Sprite="432,376 64,16" />
  <Sprite Key="Custom.StyleGaiaSelected" Sheet="battleobjects" Sprite="432,392 64,16" />
  <Sprite Key="Custom.StyleWingSelected" Sheet="battleobjects" Sprite="432,408 64,16" />
  <Sprite Key="Custom.StyleWtchSelected" Sheet="battleobjects" Sprite="432,424 64,16" />
  <Sprite Key="MainMenu.FolderUnselected" Sheet="menuwindows" Sprite="32,0 72,16" />
  <Sprite Key="MainMenu.SubChipUnselected" Sheet="menuwindows" Sprite="32,16 72,16" />
  <Sprite Key="MainMenu.LibraryUnselected" Sheet="menuwindows" Sprite="32,32 72,16" />
  <Sprite Key="MainMenu.NaviUnselected" Sheet="menuwindows" Sprite="32,48 72,16" />
  <Sprite Key="MainMenu.VirusUnselected" Sheet="menuwindows" Sprite="32,64 72,16" />
  <Sprite Key="MainMenu.MailUnselected" Sheet="menuwindows" Sprite="32,80 72,16" />
  <Sprite Key="MainMenu.KeyItemUnselected" Sheet="menuwindows" Sprite="32,96 72,16" />
  <Sprite Key="MainMenu.NetworkUnselected" Sheet="menuwindows" Sprite="32,112 72,16" />
  <Sprite Key="MainMenu.SaveUnselected" Sheet="menuwindows" Sprite="32,128 72,16" />
  <Sprite Key="MainMenu.FolderSelected" Sheet="menuwindows" Sprite="104,0 72,16" />
  <Sprite Key="MainMenu.SubChipSelected" Sheet="menuwindows" Sprite="104,16 72,16" />
  <Sprite Key="MainMenu.LibrarySelected" Sheet="menuwindows" Sprite="104,32 72,16" />
  <Sprite Key="MainMenu.NaviSelected" Sheet="menuwindows" Sprite="104,48 72,16" />
  <Sprite Key="MainMenu.VirusSelected" Sheet="menuwindows" Sprite="104,64 72,16" />
  <Sprite Key="MainMenu.MailSelected" Sheet="menuwindows" Sprite="104,80 72,16" />
  <Sprite Key="MainMenu.KeyItemSelected" Sheet="menuwindows" Sprite="104,96 72,16" />
  <Sprite Key="MainMenu.NetworkSelected" Sheet="menuwindows" Sprite="104,112 72,16" />
  <Sprite Key="MainMenu.SaveSelected" Sheet="menuwindows" Sprite="104,128 72,16" />
</data>
